minicc/__init__.py
minicc/__main__.py
minicc/cli.py
minicc/core/__init__.py
minicc/core/agent.py
minicc/core/config.py
minicc/core/events.py
minicc/core/mcp.py
minicc/core/models.py
minicc/core/runtime.py
minicc/core/services/__init__.py
minicc/core/services/ask_user.py
minicc/core/services/subagents.py
minicc/prompts/system.md
minicc/tools/__init__.py
minicc/tools/common.py
minicc/tools/file.py
minicc/tools/interact.py
minicc/tools/registry.py
minicc/tools/search.py
minicc/tools/shell.py
minicc/tools/task.py
minicc/tui/__init__.py
minicc/tui/app.py
minicc/tui/ask_user_panel.py
minicc/tui/chat_input.py
minicc/tui/file_mention_panel.py
minicc/tui/styles.tcss
minicc/tui/widgets.py
minicc-0.3.2.dist-info/METADATA
minicc-0.3.2.dist-info/WHEEL
minicc-0.3.2.dist-info/entry_points.txt
minicc-0.3.2.dist-info/RECORD
