Metadata-Version: 2.4
Name: minicc
Version: 0.3.2
Summary: Mini Claude Code - 极简教学版 AI 编程助手
Project-URL: Homepage, https://github.com/TokenRollAI/miniCC
Project-URL: Repository, https://github.com/TokenRollAI/miniCC
Project-URL: Issues, https://github.com/TokenRollAI/miniCC/issues
Author-email: DJJ <shuaiqijianhao@qq.com>
License-Expression: MIT
Keywords: agent,ai,claude,coding-assistant,pydantic-ai,tui
Classifier: Development Status :: 4 - Beta
Classifier: Environment :: Console
Classifier: Intended Audience :: Developers
Classifier: License :: OSI Approved :: MIT License
Classifier: Operating System :: OS Independent
Classifier: Programming Language :: Python :: 3.13
Classifier: Topic :: Scientific/Engineering :: Artificial Intelligence
Classifier: Topic :: Software Development :: Code Generators
Requires-Python: >=3.13
Requires-Dist: agent-gear>=0.1.3
Requires-Dist: pydantic-ai>=1.25.1
Requires-Dist: pydantic>=2.12.5
Requires-Dist: ripgrepy>=2.1.0
Requires-Dist: textual[syntax]>=6.7.0
Requires-Dist: wcmatch>=10.0
Provides-Extra: mcp
Requires-Dist: mcp>=1.18.0; extra == 'mcp'
